kgrag_store/__init__.py
kgrag_store/kgrag_cache.py
kgrag_store/kgrag_components.py
kgrag_store/kgrag_graph.py
kgrag_store/kgrag_prompt.py
kgrag_store/kgrag_utils.py
kgrag_store/kgrag_vector.py
kgrag_store/ollama/__init__.py
kgrag_store/ollama/kgrag_ollama.py
kgrag_store/openai/__init__.py
kgrag_store/openai/kgrag_openai.py
kgrag_store-2.0.3.dist-info/licenses/LICENSE.md
kgrag_store-2.0.3.dist-info/METADATA
kgrag_store-2.0.3.dist-info/WHEEL
kgrag_store-2.0.3.dist-info/top_level.txt
kgrag_store-2.0.3.dist-info/RECORD
