Metadata-Version: 2.4
Name: kgrag-store
Version: 2.0.3
Summary: A Python library for knowledge graph management and retrieval with advanced memory capabilities.
Author-email: Giuseppe Zileni <giuseppe.zileni@gmail.com>
Project-URL: Homepage, https://github.com/gzileni/kgrag-store
Project-URL: Repository, https://github.com/gzileni/kgrag-store
Keywords: agent,knowledge,memory,retrieval,vector-store,kgrag
Classifier: Programming Language :: Python :: 3
Classifier: Operating System :: OS Independent
Requires-Python: >=3.9
License-File: LICENSE.md
Requires-Dist: aioboto3==15.0.0
Requires-Dist: aiobotocore==2.23.0
Requires-Dist: aiofiles==24.1.0
Requires-Dist: aiohappyeyeballs==2.6.1
Requires-Dist: aiohttp==3.12.15
Requires-Dist: aioitertools==0.12.0
Requires-Dist: aiosignal==1.4.0
Requires-Dist: annotated-types==0.7.0
Requires-Dist: anthropic==0.64.0
Requires-Dist: anyio==4.10.0
Requires-Dist: attrs==25.3.0
Requires-Dist: backoff==2.2.1
Requires-Dist: beautifulsoup4==4.13.4
Requires-Dist: boto3==1.38.27
Requires-Dist: botocore==1.38.27
Requires-Dist: build==1.3.0
Requires-Dist: certifi==2025.8.3
Requires-Dist: cffi==1.17.1
Requires-Dist: chardet==5.2.0
Requires-Dist: charset-normalizer==3.4.3
Requires-Dist: click==8.2.1
Requires-Dist: coloredlogs==15.0.1
Requires-Dist: contourpy==1.3.3
Requires-Dist: cryptography==45.0.6
Requires-Dist: cycler==0.12.1
Requires-Dist: dataclasses-json==0.6.7
Requires-Dist: distro==1.9.0
Requires-Dist: docutils==0.22
Requires-Dist: dydantic==0.0.8
Requires-Dist: emoji==2.14.1
Requires-Dist: fastembed==0.7.1
Requires-Dist: filelock==3.18.0
Requires-Dist: filetype==1.2.0
Requires-Dist: flatbuffers==25.2.10
Requires-Dist: fonttools==4.59.0
Requires-Dist: fpdf==1.7.2
Requires-Dist: frozenlist==1.7.0
Requires-Dist: fsspec==2024.12.0
Requires-Dist: greenlet==3.2.4
Requires-Dist: grpcio==1.74.0
Requires-Dist: h11==0.16.0
Requires-Dist: h2==4.2.0
Requires-Dist: hf-xet==1.1.7
Requires-Dist: hpack==4.1.0
Requires-Dist: html5lib==1.1
Requires-Dist: httpcore==1.0.9
Requires-Dist: httpx==0.28.1
Requires-Dist: httpx-sse==0.4.1
Requires-Dist: huggingface-hub==0.34.4
Requires-Dist: humanfriendly==10.0
Requires-Dist: hyperframe==6.1.0
Requires-Dist: id==1.5.0
Requires-Dist: idna==3.10
Requires-Dist: iniconfig==2.1.0
Requires-Dist: jaraco.classes==3.4.0
Requires-Dist: jaraco.context==6.0.1
Requires-Dist: jaraco.functools==4.2.1
Requires-Dist: jiter==0.10.0
Requires-Dist: jmespath==1.0.1
Requires-Dist: joblib==1.5.1
Requires-Dist: json_repair==0.44.1
Requires-Dist: jsonpatch==1.33
Requires-Dist: jsonpointer==3.0.0
Requires-Dist: keyring==25.6.0
Requires-Dist: kiwisolver==1.4.9
Requires-Dist: langchain==0.3.27
Requires-Dist: langchain-anthropic==0.3.19
Requires-Dist: langchain-community==0.3.27
Requires-Dist: langchain-core==0.3.75
Requires-Dist: langchain-ollama==0.3.6
Requires-Dist: langchain-openai==0.3.30
Requires-Dist: langchain-qdrant==0.2.0
Requires-Dist: langchain-text-splitters==0.3.10
Requires-Dist: langcodes==3.5.0
Requires-Dist: langdetect==1.0.9
Requires-Dist: langgraph==0.6.6
Requires-Dist: langgraph-checkpoint==2.1.1
Requires-Dist: langgraph-prebuilt==0.6.4
Requires-Dist: langgraph-sdk==0.2.4
Requires-Dist: langmem==0.0.29
Requires-Dist: langsmith==0.4.14
Requires-Dist: language_data==1.3.0
Requires-Dist: loguru==0.7.3
Requires-Dist: loki-logger-handler==1.1.2
Requires-Dist: lxml==6.0.0
Requires-Dist: marisa-trie==1.3.1
Requires-Dist: Markdown==3.8.2
Requires-Dist: markdown-it-py==4.0.0
Requires-Dist: marshmallow==3.26.1
Requires-Dist: matplotlib==3.10.5
Requires-Dist: mdurl==0.1.2
Requires-Dist: memory_agent==2.1.2
Requires-Dist: mmh3==5.2.0
Requires-Dist: more-itertools==10.7.0
Requires-Dist: mpmath==1.3.0
Requires-Dist: multidict==6.6.4
Requires-Dist: mypy_extensions==1.1.0
Requires-Dist: narwhals==2.1.1
Requires-Dist: neo4j==5.28.2
Requires-Dist: neo4j-graphrag==1.9.1
Requires-Dist: nest-asyncio==1.6.0
Requires-Dist: nh3==0.3.0
Requires-Dist: nltk==3.9.1
Requires-Dist: numpy==2.3.2
Requires-Dist: olefile==0.47
Requires-Dist: ollama==0.5.3
Requires-Dist: onnxruntime==1.22.1
Requires-Dist: openai==1.99.9
Requires-Dist: orjson==3.11.2
Requires-Dist: ormsgpack==1.10.0
Requires-Dist: packaging==25.0
Requires-Dist: pandas==2.3.1
Requires-Dist: pillow==11.3.0
Requires-Dist: plotly==6.3.0
Requires-Dist: pluggy==1.6.0
Requires-Dist: portalocker==3.2.0
Requires-Dist: propcache==0.3.2
Requires-Dist: protobuf==6.31.1
Requires-Dist: psutil==7.0.0
Requires-Dist: py_rust_stemmers==0.1.5
Requires-Dist: pyaws-s3==1.0.28
Requires-Dist: pycparser==2.22
Requires-Dist: pydantic==2.11.7
Requires-Dist: pydantic-settings==2.10.1
Requires-Dist: pydantic_core==2.33.2
Requires-Dist: Pygments==2.19.2
Requires-Dist: pyparsing==3.2.3
Requires-Dist: pypdf==5.9.0
Requires-Dist: pyproject_hooks==1.2.0
Requires-Dist: pytest==8.4.1
Requires-Dist: python-dateutil==2.9.0.post0
Requires-Dist: python-dotenv==1.1.1
Requires-Dist: python-iso639==2025.2.18
Requires-Dist: python-magic==0.4.27
Requires-Dist: python-oxmsg==0.0.2
Requires-Dist: pytz==2025.2
Requires-Dist: PyYAML==6.0.2
Requires-Dist: qdrant-client==1.15.1
Requires-Dist: RapidFuzz==3.13.0
Requires-Dist: readme_renderer==44.0
Requires-Dist: redis==6.4.0
Requires-Dist: regex==2025.7.34
Requires-Dist: reportlab==4.4.3
Requires-Dist: requests==2.32.4
Requires-Dist: requests-toolbelt==1.0.0
Requires-Dist: rfc3986==2.0.0
Requires-Dist: rich==14.1.0
Requires-Dist: s3transfer==0.13.1
Requires-Dist: scipy==1.16.1
Requires-Dist: setuptools==80.9.0
Requires-Dist: six==1.17.0
Requires-Dist: sniffio==1.3.1
Requires-Dist: soupsieve==2.7
Requires-Dist: SQLAlchemy==2.0.43
Requires-Dist: sympy==1.14.0
Requires-Dist: tenacity==9.1.2
Requires-Dist: tiktoken==0.11.0
Requires-Dist: tokenizers==0.21.4
Requires-Dist: tqdm==4.67.1
Requires-Dist: trustcall==0.0.39
Requires-Dist: twine==6.1.0
Requires-Dist: types-PyYAML==6.0.12.20250809
Requires-Dist: typing-inspect==0.9.0
Requires-Dist: typing-inspection==0.4.1
Requires-Dist: typing_extensions==4.14.1
Requires-Dist: tzdata==2025.2
Requires-Dist: unstructured==0.18.11
Requires-Dist: unstructured-client==0.42.3
Requires-Dist: urllib3==2.5.0
Requires-Dist: webencodings==0.5.1
Requires-Dist: wheel==0.45.1
Requires-Dist: wrapt==1.17.3
Requires-Dist: xxhash==3.5.0
Requires-Dist: yarl==1.20.1
Requires-Dist: zstandard==0.23.0
Dynamic: license-file
